lollylib/__init__.py
lollylib/lolly_helpers.py
lollylib/lolly_wiz.py
lollylib/lolly_wizzoo.py
lollylib/test.py
lollylib/assets/lollywiz_templates/git/CONTRIBUTING.md.lwt
lollylib/assets/lollywiz_templates/git/MIT_LICENSE.lwt
lollylib/assets/lollywiz_templates/git/README.md.lwt
lollylib/assets/lollywiz_templates/git/gitignore.lwt
lollylib/assets/lollywiz_templates/git/lollywiz.txt
lollylib/tests/__init__.py
lollylib/tests/test_lolly_helpers.py
lollylib/tests/test_lolly_wiz.py
lollylib/tests/__pycache__/__init__.cpython-35.pyc
lollylib/tests/__pycache__/__init__.cpython-37.pyc
lollylib/tests/__pycache__/run_all_tests.cpython-37.pyc
lollylib/tests/__pycache__/test_lolly_helpers.cpython-37.pyc
lollylib/tests/__pycache__/test_lolly_wiz.cpython-37.pyc
lollylib/tests/test_data/lollyhelpers/existing_test_file.txt
lollylib/tests/test_data/lollywiz/condition_tests/cond_result1.hpp
lollylib/tests/test_data/lollywiz/condition_tests/cond_template1.hpp
lollylib/tests/test_data/lollywiz/condition_tests/lollywiz.txt
lollylib/tests/test_data/lollywiz/generic_tests/lollywiz.txt
lollylib/tests/test_data/lollywiz/generic_tests/test_dir/test.txt
lollylib/tests/test_data/lollywiz/instantiation_tests/lollywiz.txt
lollylib/tests/test_data/lollywiz/instantiation_tests/template0.hpp
lollylib/tests/test_data/lollywiz/instantiation_tests/template1.hpp
lollylib/tests/test_data/lollywiz/instantiation_tests/verify1.txt
lollylib/tests/test_data/lollywiz/instantiation_tests/verify2.txt
lollylib-0.1.0.dist-info/LICENSE
lollylib-0.1.0.dist-info/METADATA
lollylib-0.1.0.dist-info/WHEEL
lollylib-0.1.0.dist-info/top_level.txt
lollylib-0.1.0.dist-info/RECORD
