Metadata-Version: 2.1
Name: lollylib
Version: 0.1.0
Summary: A multipurpose Python 3 library that creates an additional abstraction layer                     and provides higher level interface for python developers
Home-page: https://github.com/sugurd/lollylib
Author: Yuri Zappa
Author-email: yuzappa@gmail.com
License: MIT
Keywords: lollylib
Platform: UNKNOWN
Classifier: Development Status :: 3 - Alpha
Classifier: License :: OSI Approved :: MIT License
Classifier: Programming Language :: Python :: 3
Classifier: Topic :: Software Development :: Libraries :: Python Modules
Requires-Dist: markdown
Requires-Dist: semver
